_notion_scripts/__init__.py
_notion_scripts/upload.py
sphinx_notion/__init__.py
sphinx_notion/py.typed
sphinx_notionbuilder-2026.1.11.dist-info/licenses/LICENSE
sphinx_notionbuilder-2026.1.11.dist-info/METADATA
sphinx_notionbuilder-2026.1.11.dist-info/WHEEL
sphinx_notionbuilder-2026.1.11.dist-info/entry_points.txt
sphinx_notionbuilder-2026.1.11.dist-info/top_level.txt
sphinx_notionbuilder-2026.1.11.dist-info/RECORD
