Metadata-Version: 2.4
Name: sphinx-notionbuilder
Version: 2026.1.11
Summary: Sphinx extension to build Notion pages.
Author-email: Adam Dangoor <adamdangoor@gmail.com>
License-Expression: MIT
Project-URL: Source, https://github.com/adamtheturtle/sphinx-notionbuilder
Keywords: notion,sphinx
Classifier: Development Status :: 5 - Production/Stable
Classifier: Environment :: Web Environment
Classifier: Operating System :: Microsoft :: Windows
Classifier: Operating System :: POSIX
Classifier: Programming Language :: Python :: 3 :: Only
Classifier: Programming Language :: Python :: 3.12
Classifier: Programming Language :: Python :: 3.13
Requires-Python: >=3.12
License-File: LICENSE
Requires-Dist: atsphinx-audioplayer>=0.2.1
Requires-Dist: beartype>=0.21.0
Requires-Dist: beautifulsoup4>=4.13.3
Requires-Dist: click>=8.0.0
Requires-Dist: cloup>=3.0.0
Requires-Dist: docutils>=0.21
Requires-Dist: requests>=2.32.5
Requires-Dist: sphinx>=8.2.3
Requires-Dist: sphinx-iframes>=1.1.0
Requires-Dist: sphinx-immaterial>=0.13.7
Requires-Dist: sphinx-simplepdf>=1.6.0
Requires-Dist: sphinx-toolbox>=4.0.0
Requires-Dist: sphinxcontrib-video>=0.4.0
Requires-Dist: sphinxnotes-strike>=2.0
Requires-Dist: ultimate-notion>=0.9.6
Provides-Extra: dev
Requires-Dist: actionlint-py==1.7.10.24; extra == "dev"
Requires-Dist: anstrip==0.2.2; extra == "dev"
Requires-Dist: check-manifest==0.51; extra == "dev"
Requires-Dist: deptry==0.24.0; extra == "dev"
Requires-Dist: doc8==2.0.0; extra == "dev"
Requires-Dist: doccmd==2026.1.3.2; extra == "dev"
Requires-Dist: docformatter==1.7.7; extra == "dev"
Requires-Dist: freezegun==1.5.5; extra == "dev"
Requires-Dist: furo==2025.12.19; extra == "dev"
Requires-Dist: interrogate==1.7.0; extra == "dev"
Requires-Dist: mypy[faster-cache]==1.19.1; extra == "dev"
Requires-Dist: mypy-strict-kwargs==2025.4.3; extra == "dev"
Requires-Dist: prek==0.2.27; extra == "dev"
Requires-Dist: pydocstyle==6.3; extra == "dev"
Requires-Dist: pygments==2.19.2; extra == "dev"
Requires-Dist: pylint[spelling]==4.0.4; extra == "dev"
Requires-Dist: pylint-per-file-ignores==3.2.0; extra == "dev"
Requires-Dist: pyproject-fmt==2.11.1; extra == "dev"
Requires-Dist: pyrefly==0.47.0; extra == "dev"
Requires-Dist: pyright==1.1.408; extra == "dev"
Requires-Dist: pyroma==5.0.1; extra == "dev"
Requires-Dist: pytest==9.0.2; extra == "dev"
Requires-Dist: pytest-cov==7.0.0; extra == "dev"
Requires-Dist: pytest-regressions==2.9.0; extra == "dev"
Requires-Dist: pyyaml==6.0.3; extra == "dev"
Requires-Dist: ruff==0.14.11; extra == "dev"
Requires-Dist: shellcheck-py==0.11.0.1; extra == "dev"
Requires-Dist: shfmt-py==3.12.0.2; extra == "dev"
Requires-Dist: sphinx-lint==1.0.2; extra == "dev"
Requires-Dist: sphinx-pyproject==0.3.0; extra == "dev"
Requires-Dist: sphinx-substitution-extensions==2025.12.15; extra == "dev"
Requires-Dist: sphinxcontrib-spelling==8.0.2; extra == "dev"
Requires-Dist: sphinxcontrib-text-styles==0.2.1; extra == "dev"
Requires-Dist: ty==0.0.10; extra == "dev"
Requires-Dist: types-docutils==0.22.3.20251115; extra == "dev"
Requires-Dist: types-requests==2.32.4.20260107; extra == "dev"
Requires-Dist: vulture==2.14; extra == "dev"
Requires-Dist: yamlfix==1.19.1; extra == "dev"
Requires-Dist: zizmor==1.20.0; extra == "dev"
Provides-Extra: release
Requires-Dist: check-wheel-contents==0.6.3; extra == "release"
Provides-Extra: sample
Requires-Dist: sphinxcontrib-text-styles==0.2.1; extra == "sample"
Dynamic: license-file
